jadia/__init__.py
jadia/audio.py
jadia/coskmeans.py
jadia/gaussian.py
jadia/hungarian.py
jadia/main.py
jadia/metrics.py
jadia/models.py
jadia/segment.py
jadia/assets/lite.pt
jadia/assets/lite_v2.pt
jadia/assets/mel_filters.npz
jadia-0.1.1.dist-info/LICENSE
jadia-0.1.1.dist-info/METADATA
jadia-0.1.1.dist-info/WHEEL
jadia-0.1.1.dist-info/top_level.txt
jadia-0.1.1.dist-info/RECORD
