Metadata-Version: 2.1
Name: jadia
Version: 0.1.1
Summary: JaNet diarization package
Author-email: Sergey Skrebnev <sergey.skrebnev@gmail.com>
Project-URL: Homepage, https://github.com/skrbnv/jadia
Classifier: Programming Language :: Python :: 3
Classifier: License :: OSI Approved :: MIT License
Classifier: Operating System :: OS Independent
Requires-Python: >=3.0
License-File: LICENSE
Requires-Dist: librosa >=0.10.1
Requires-Dist: numpy >=2.1.0
Requires-Dist: silero-vad >=5.1
Requires-Dist: soundfile >=0.12.1
Requires-Dist: soxr >=0.3.7
Requires-Dist: torch >=2.4.0
